cluster_agent/__init__.py
cluster_agent/agent.py
cluster_agent/main.py
cluster_agent/settings.py
cluster_agent/identity/__init__.py
cluster_agent/identity/cluster_api.py
cluster_agent/identity/slurmrestd.py
cluster_agent/identity/slurm_user/__init__.py
cluster_agent/identity/slurm_user/constants.py
cluster_agent/identity/slurm_user/exceptions.py
cluster_agent/identity/slurm_user/factory.py
cluster_agent/identity/slurm_user/mappers/__init__.py
cluster_agent/identity/slurm_user/mappers/ldap.py
cluster_agent/identity/slurm_user/mappers/mapper_base.py
cluster_agent/identity/slurm_user/mappers/single_user.py
cluster_agent/jobbergate/__init__.py
cluster_agent/jobbergate/api.py
cluster_agent/jobbergate/constants.py
cluster_agent/jobbergate/finish.py
cluster_agent/jobbergate/schemas.py
cluster_agent/jobbergate/submit.py
cluster_agent/scripts/__init__.py
cluster_agent/scripts/agentconfig.py
cluster_agent/utils/__init__.py
cluster_agent/utils/exception.py
cluster_agent/utils/logging.py
tests/__init__.py
tests/conftest.py
tests/test_agent.py
tests/test_main.py
tests/test_settings.py
tests/identity/__init__.py
tests/identity/test_cluster_api_identity.py
tests/identity/test_slurmrestd_identity.py
tests/jobbergate/__init__.py
tests/jobbergate/conftest.py
tests/jobbergate/test_api.py
tests/jobbergate/test_finish.py
tests/jobbergate/test_submit.py
ovs_cluster_agent-2.2.3.dist-info/LICENSE
ovs_cluster_agent-2.2.3.dist-info/METADATA
ovs_cluster_agent-2.2.3.dist-info/WHEEL
ovs_cluster_agent-2.2.3.dist-info/entry_points.txt
ovs_cluster_agent-2.2.3.dist-info/top_level.txt
ovs_cluster_agent-2.2.3.dist-info/RECORD
