Metadata-Version: 2.1
Name: ovs-cluster-agent
Version: 2.2.3
Summary: Cluster API data aggregator
Home-page: https://github.com/omnivector-solutions/ovs-cluster-agent/
Author: omnivector-solutions
Author-email: info@omnivector.solutions
License: MIT
Download-URL: https://github.com/omnivector-solutions/ovs-cluster-agent/dist/cluster-agent-2.2.3tar.gz
Keywords: armada,hpc
Platform: UNKNOWN
Classifier: Development Status :: 4 - Beta
Classifier: Intended Audience :: Developers
Classifier: Intended Audience :: Information Technology
Classifier: Intended Audience :: System Administrators
Classifier: Intended Audience :: Other Audience
Classifier: Topic :: Software Development
Classifier: Topic :: Internet
Classifier: Topic :: Internet :: WWW/HTTP :: HTTP Servers
Classifier: Topic :: Utilities
Classifier: License :: Other/Proprietary License
Classifier: Programming Language :: Python :: 3
Classifier: Programming Language :: Python :: 3.8
Classifier: Operating System :: OS Independent
Requires-Dist: boto3 (==1.17.8)
Requires-Dist: Codado (==0.8.0)
Requires-Dist: click (==8.0.1)
Requires-Dist: pydantic (==1.8.2)
Requires-Dist: python-dotenv (==0.16.0)
Requires-Dist: toml (==0.10.2)
Requires-Dist: sentry-sdk (~=1.1.0)
Requires-Dist: python-hostlist (==1.21)
Requires-Dist: loguru (==0.6.0)
Requires-Dist: httpx (==0.23.0)
Requires-Dist: py-buzz (==3.1.0)
Requires-Dist: ldap3 (==2.9.1)
Requires-Dist: python-jose (==3.3.0)
Requires-Dist: timeoutcontext (==1.2.0)
Provides-Extra: dev
Requires-Dist: pytest (==7.1.0) ; extra == 'dev'
Requires-Dist: pytest-mock (==3.7.0) ; extra == 'dev'
Requires-Dist: respx (==0.19.2) ; extra == 'dev'
Requires-Dist: asynctest (==0.13.0) ; extra == 'dev'
Requires-Dist: pytest-asyncio (==0.18.2) ; extra == 'dev'
Requires-Dist: black (==22.3.0) ; extra == 'dev'
Requires-Dist: flake8 (==4.0.1) ; extra == 'dev'
Requires-Dist: pytest-env (==0.6.2) ; extra == 'dev'
Requires-Dist: pytest-random-order (==1.0.4) ; extra == 'dev'
Requires-Dist: pytest-cov (==3.0.0) ; extra == 'dev'
Requires-Dist: freezegun (==1.2.2) ; extra == 'dev'
